manasrag/__init__.py
manasrag/_logging.py
manasrag/cli.py
manasrag/document_loader.py
manasrag/prompts.py
manasrag/api/__init__.py
manasrag/api/app.py
manasrag/api/dependencies.py
manasrag/api/models.py
manasrag/api/routes_manas.py
manasrag/api/routes_openai.py
manasrag/api/streaming.py
manasrag/components/AGENTS.md
manasrag/components/__init__.py
manasrag/components/community_detector.py
manasrag/components/entity_extractor.py
manasrag/components/graph_visualizer.py
manasrag/components/hierarchical_entity_extractor.py
manasrag/components/hierarchical_retriever.py
manasrag/components/path_finder.py
manasrag/components/report_generator.py
manasrag/core/__init__.py
manasrag/core/community.py
manasrag/core/graph.py
manasrag/core/query_param.py
manasrag/pipelines/__init__.py
manasrag/pipelines/indexing.py
manasrag/pipelines/query.py
manasrag/stores/AGENTS.md
manasrag/stores/__init__.py
manasrag/stores/base.py
manasrag/stores/neo4j_store.py
manasrag/stores/networkx_store.py
manasrag/stores/vector_store.py
manasrag/utils/__init__.py
manasrag/utils/color_utils.py
manasrag/utils/token_utils.py
manasrag-0.1.1.dist-info/METADATA
manasrag-0.1.1.dist-info/WHEEL
manasrag-0.1.1.dist-info/entry_points.txt
manasrag-0.1.1.dist-info/RECORD
