Metadata-Version: 2.4
Name: manasrag
Version: 0.1.1
Summary: Hierarchical Retrieval-Augmented Generation with Haystack
Project-URL: Homepage, https://github.com/yourusername/manasrag
Project-URL: Documentation, https://github.com/yourusername/manasrag#readme
Project-URL: Source, https://github.com/yourusername/manasrag
Author-email: Your Name <your.email@example.com>
License: MIT
Keywords: haystack,hierarchical,knowledge-graph,llm,rag
Classifier: Development Status :: 3 - Alpha
Classifier: Intended Audience :: Developers
Classifier: License :: OSI Approved :: MIT License
Classifier: Programming Language :: Python :: 3.10
Classifier: Programming Language :: Python :: 3.11
Classifier: Programming Language :: Python :: 3.12
Requires-Python: >=3.10
Requires-Dist: click>=8.0
Requires-Dist: haystack-ai>=2.6
Requires-Dist: networkx
Requires-Dist: python-dotenv
Requires-Dist: python-louvain
Requires-Dist: pyyaml
Requires-Dist: tiktoken
Provides-Extra: all
Requires-Dist: boilerpy3; extra == 'all'
Requires-Dist: coverage[toml]; extra == 'all'
Requires-Dist: fastapi>=0.104.0; extra == 'all'
Requires-Dist: haystack-ai[openai]; extra == 'all'
Requires-Dist: kaleido>=0.2.0; extra == 'all'
Requires-Dist: markdown-it-py; extra == 'all'
Requires-Dist: neo4j>=5.0; extra == 'all'
Requires-Dist: openai>=1.0; extra == 'all'
Requires-Dist: openpyxl; extra == 'all'
Requires-Dist: plotly>=5.18.0; extra == 'all'
Requires-Dist: pypdf; extra == 'all'
Requires-Dist: pytest-asyncio>=0.21; extra == 'all'
Requires-Dist: pytest>=7.0; extra == 'all'
Requires-Dist: python-docx; extra == 'all'
Requires-Dist: pyvis>=0.3.2; extra == 'all'
Requires-Dist: scikit-learn; extra == 'all'
Requires-Dist: uvicorn[standard]>=0.24.0; extra == 'all'
Provides-Extra: api
Requires-Dist: fastapi>=0.104.0; extra == 'api'
Requires-Dist: uvicorn[standard]>=0.24.0; extra == 'api'
Provides-Extra: cli
Requires-Dist: boilerpy3; extra == 'cli'
Requires-Dist: markdown-it-py; extra == 'cli'
Requires-Dist: openpyxl; extra == 'cli'
Requires-Dist: pypdf; extra == 'cli'
Requires-Dist: python-docx; extra == 'cli'
Provides-Extra: dev
Requires-Dist: coverage[toml]; extra == 'dev'
Requires-Dist: pytest-asyncio>=0.21; extra == 'dev'
Requires-Dist: pytest>=7.0; extra == 'dev'
Provides-Extra: neo4j
Requires-Dist: neo4j>=5.0; extra == 'neo4j'
Provides-Extra: openai
Requires-Dist: haystack-ai[openai]; extra == 'openai'
Requires-Dist: openai>=1.0; extra == 'openai'
Provides-Extra: scikit-learn
Requires-Dist: scikit-learn; extra == 'scikit-learn'
Provides-Extra: visualization
Requires-Dist: kaleido>=0.2.0; extra == 'visualization'
Requires-Dist: plotly>=5.18.0; extra == 'visualization'
Requires-Dist: pyvis>=0.3.2; extra == 'visualization'
